karrio/mappers/canadapost/__init__.py
karrio/mappers/canadapost/mapper.py
karrio/mappers/canadapost/proxy.py
karrio/mappers/canadapost/settings.py
karrio/plugins/canadapost/__init__.py
karrio/providers/canadapost/__init__.py
karrio/providers/canadapost/error.py
karrio/providers/canadapost/manifest.py
karrio/providers/canadapost/rate.py
karrio/providers/canadapost/tracking.py
karrio/providers/canadapost/units.py
karrio/providers/canadapost/utils.py
karrio/providers/canadapost/pickup/__init__.py
karrio/providers/canadapost/pickup/cancel.py
karrio/providers/canadapost/pickup/create.py
karrio/providers/canadapost/pickup/update.py
karrio/providers/canadapost/shipment/__init__.py
karrio/providers/canadapost/shipment/cancel.py
karrio/providers/canadapost/shipment/create.py
karrio/schemas/canadapost/__init__.py
karrio/schemas/canadapost/authreturn.py
karrio/schemas/canadapost/common.py
karrio/schemas/canadapost/customerinfo.py
karrio/schemas/canadapost/discovery.py
karrio/schemas/canadapost/manifest.py
karrio/schemas/canadapost/merchantregistration.py
karrio/schemas/canadapost/messages.py
karrio/schemas/canadapost/ncshipment.py
karrio/schemas/canadapost/openreturn.py
karrio/schemas/canadapost/pickup.py
karrio/schemas/canadapost/pickuprequest.py
karrio/schemas/canadapost/postoffice.py
karrio/schemas/canadapost/rating.py
karrio/schemas/canadapost/serviceinfo.py
karrio/schemas/canadapost/shipment.py
karrio/schemas/canadapost/track.py
karrio_canadapost-2026.1.4.dist-info/METADATA
karrio_canadapost-2026.1.4.dist-info/WHEEL
karrio_canadapost-2026.1.4.dist-info/entry_points.txt
karrio_canadapost-2026.1.4.dist-info/top_level.txt
karrio_canadapost-2026.1.4.dist-info/RECORD
